AUTHORS.rst
CONTRIBUTING.rst
HISTORY.rst
LICENSE
MANIFEST.in
README.rst
setup.cfg
setup.py
docs/Makefile
docs/api.rst
docs/authors.rst
docs/conf.py
docs/contributing.rst
docs/history.rst
docs/index.rst
docs/make.bat
docs/model_basics.rst
docs/usage.rst
docs/_build/html/_downloads/0686a03da72ef988337b900e8aa209e5/one-diode.hires.png
docs/_build/html/_downloads/ee2294afa81cddfca0cc7ca7c9fffed2/one-diode.png
docs/_build/html/_images/irrad_vs_Jsc.png
docs/_build/html/_images/logo.png
docs/_build/html/_images/one-diode.png
docs/_build/html/_images/sphx_glr_plot_bifacial_basics_001.png
docs/_build/html/_images/sphx_glr_plot_bifacial_basics_002.png
docs/_build/html/_images/sphx_glr_plot_bifacial_basics_003.png
docs/_build/html/_images/sphx_glr_plot_bifacial_basics_thumb.png
docs/_build/html/_images/sphx_glr_plot_bifacial_energy_yield_001.png
docs/_build/html/_images/sphx_glr_plot_bifacial_energy_yield_thumb.png
docs/_build/html/_images/sphx_glr_plot_bifacial_irradiance_yield_001.png
docs/_build/html/_images/sphx_glr_plot_bifacial_irradiance_yield_002.png
docs/_build/html/_images/sphx_glr_plot_bifacial_irradiance_yield_thumb.png
docs/_build/html/_images/sphx_glr_plot_jph_from_spec_001.png
docs/_build/html/_images/sphx_glr_plot_jph_from_spec_002.png
docs/_build/html/_images/sphx_glr_plot_jph_from_spec_003.png
docs/_build/html/_images/sphx_glr_plot_jph_from_spec_thumb.png
docs/_build/html/_images/sphx_glr_plot_silicon_ey_001.png
docs/_build/html/_images/sphx_glr_plot_silicon_ey_thumb.png
docs/_build/html/_images/sphx_glr_plot_tandem_2t_stc_001.png
docs/_build/html/_images/sphx_glr_plot_tandem_2t_stc_thumb.png
docs/_build/html/_images/sphx_glr_plot_tandem_4t_stc_001.png
docs/_build/html/_images/sphx_glr_plot_tandem_4t_stc_thumb.png
docs/_build/html/_images/sphx_glr_plot_tandem_ey_001.png
docs/_build/html/_images/sphx_glr_plot_tandem_ey_thumb.png
docs/_build/html/_images/sphx_glr_plot_tandem_optim_bg_stc_001.png
pv_tandem.egg-info/PKG-INFO
pv_tandem.egg-info/SOURCES.txt
pv_tandem.egg-info/dependency_links.txt
pv_tandem.egg-info/not-zip-safe
pv_tandem.egg-info/requires.txt
pv_tandem.egg-info/top_level.txt
