Metadata-Version: 2.1
Name: pv-tandem
Version: 0.1.1
Summary: Python toolbox for simulation and energy yield calculations of tandem solar cells.
Home-page: https://github.com/nano-sippe/pv_tandem
Author: Peter Tillmann
Author-email: Peter.tillmann@helmholtz-berlin.de
License: MIT license
Keywords: pv_tandem
Classifier: Development Status :: 3 - Alpha
Classifier: Intended Audience :: Developers
Classifier: License :: OSI Approved :: MIT License
Classifier: Natural Language :: English
Classifier: Programming Language :: Python :: 3
Classifier: Programming Language :: Python :: 3.6
Classifier: Programming Language :: Python :: 3.7
Classifier: Programming Language :: Python :: 3.8
Requires-Python: >=3.6
Provides-Extra: optional
Provides-Extra: doc
Provides-Extra: test
Provides-Extra: all
License-File: LICENSE
License-File: AUTHORS.rst
